awsiot/__init__.py
awsiot/eventstreamrpc.py
awsiot/greengrass_discovery.py
awsiot/iotidentity.py
awsiot/iotjobs.py
awsiot/iotshadow.py
awsiot/mqtt5_client_builder.py
awsiot/mqtt_connection_builder.py
awsiot/greengrasscoreipc/__init__.py
awsiot/greengrasscoreipc/client.py
awsiot/greengrasscoreipc/clientv2.py
awsiot/greengrasscoreipc/model.py
awsiotsdk-1.27.0.dist-info/METADATA
awsiotsdk-1.27.0.dist-info/WHEEL
awsiotsdk-1.27.0.dist-info/top_level.txt
awsiotsdk-1.27.0.dist-info/RECORD
