Metadata-Version: 2.4
Name: awsiotsdk
Version: 1.27.0
Summary: AWS IoT SDK based on the AWS Common Runtime
Home-page: https://github.com/aws/aws-iot-device-sdk-python-v2
Author: AWS SDK Common Runtime Team
License: License :: OSI Approved :: Apache Software License
Classifier: Programming Language :: Python :: 3
Classifier: License :: OSI Approved :: Apache Software License
Classifier: Operating System :: OS Independent
Requires-Python: >=3.8
Requires-Dist: awscrt==0.30.0
Dynamic: author
Dynamic: classifier
Dynamic: description
Dynamic: description-content-type
Dynamic: home-page
Dynamic: license
Dynamic: requires-dist
Dynamic: requires-python
Dynamic: summary
